<?xml version="1.0" encoding="UTF-8"?>
<?xml-stylesheet href="persister-table.xsl" type="text/xsl"?>
<beans xmlns="http://www.springframework.org/schema/beans"
       xmlns:xsi="http://www.w3.org/2001/XMLSchema-instance"
       xmlns:aop="http://www.springframework.org/schema/aop"
       xmlns:context="http://www.springframework.org/schema/context"
       xsi:schemaLocation="http://www.springframework.org/schema/beans 
                           http://www.springframework.org/schema/beans/spring-beans-2.5.xsd
                           http://www.springframework.org/schema/aop 
                           http://www.springframework.org/schema/aop/spring-aop-2.5.xsd
                           http://www.springframework.org/schema/context 
                           http://www.springframework.org/schema/context/spring-context-2.5.xsd">

<bean id="FXFWDMarketJPYCZK-ON-Market-Publisher" class="com.eurobase.ratemanager.external.out.RatePublisher">
  <constructor-arg index="0">
    <value>FXFWDMarketJPYCZK-ON-Market-Publisher</value>
  </constructor-arg>
  <property name="rateBean">
    <ref bean="FXFWDMarketJPYCZK-ON-Market-RateBean"/>
  </property>
  <property name="service">
    <ref bean="publisherService"/>
  </property>
  <property name="auditor">
    <ref bean="auditor"/>
  </property>
</bean>

<bean id="FXFWDMarketJPYCZK-TN-Market-Publisher" class="com.eurobase.ratemanager.external.out.RatePublisher">
  <constructor-arg index="0">
    <value>FXFWDMarketJPYCZK-TN-Market-Publisher</value>
  </constructor-arg>
  <property name="rateBean">
    <ref bean="FXFWDMarketJPYCZK-TN-Market-RateBean"/>
  </property>
  <property name="service">
    <ref bean="publisherService"/>
  </property>
  <property name="auditor">
    <ref bean="auditor"/>
  </property>
</bean>

<bean id="FXFWDMarketJPYCZK-SN-Market-Publisher" class="com.eurobase.ratemanager.external.out.RatePublisher">
  <constructor-arg index="0">
    <value>FXFWDMarketJPYCZK-SN-Market-Publisher</value>
  </constructor-arg>
  <property name="rateBean">
    <ref bean="FXFWDMarketJPYCZK-SN-Market-RateBean"/>
  </property>
  <property name="service">
    <ref bean="publisherService"/>
  </property>
  <property name="auditor">
    <ref bean="auditor"/>
  </property>
</bean>

<bean id="FXFWDMarketJPYCZK-1W-Market-Publisher" class="com.eurobase.ratemanager.external.out.RatePublisher">
  <constructor-arg index="0">
    <value>FXFWDMarketJPYCZK-1W-Market-Publisher</value>
  </constructor-arg>
  <property name="rateBean">
    <ref bean="FXFWDMarketJPYCZK-1W-Market-RateBean"/>
  </property>
  <property name="service">
    <ref bean="publisherService"/>
  </property>
  <property name="auditor">
    <ref bean="auditor"/>
  </property>
</bean>

<bean id="FXFWDMarketJPYCZK-2W-Market-Publisher" class="com.eurobase.ratemanager.external.out.RatePublisher">
  <constructor-arg index="0">
    <value>FXFWDMarketJPYCZK-2W-Market-Publisher</value>
  </constructor-arg>
  <property name="rateBean">
    <ref bean="FXFWDMarketJPYCZK-2W-Market-RateBean"/>
  </property>
  <property name="service">
    <ref bean="publisherService"/>
  </property>
  <property name="auditor">
    <ref bean="auditor"/>
  </property>
</bean>

<bean id="FXFWDMarketJPYCZK-3W-Market-Publisher" class="com.eurobase.ratemanager.external.out.RatePublisher">
  <constructor-arg index="0">
    <value>FXFWDMarketJPYCZK-3W-Market-Publisher</value>
  </constructor-arg>
  <property name="rateBean">
    <ref bean="FXFWDMarketJPYCZK-3W-Market-RateBean"/>
  </property>
  <property name="service">
    <ref bean="publisherService"/>
  </property>
  <property name="auditor">
    <ref bean="auditor"/>
  </property>
</bean>

<bean id="FXFWDMarketJPYCZK-1M-Market-Publisher" class="com.eurobase.ratemanager.external.out.RatePublisher">
  <constructor-arg index="0">
    <value>FXFWDMarketJPYCZK-1M-Market-Publisher</value>
  </constructor-arg>
  <property name="rateBean">
    <ref bean="FXFWDMarketJPYCZK-1M-Market-RateBean"/>
  </property>
  <property name="service">
    <ref bean="publisherService"/>
  </property>
  <property name="auditor">
    <ref bean="auditor"/>
  </property>
</bean>

<bean id="FXFWDMarketJPYCZK-2M-Market-Publisher" class="com.eurobase.ratemanager.external.out.RatePublisher">
  <constructor-arg index="0">
    <value>FXFWDMarketJPYCZK-2M-Market-Publisher</value>
  </constructor-arg>
  <property name="rateBean">
    <ref bean="FXFWDMarketJPYCZK-2M-Market-RateBean"/>
  </property>
  <property name="service">
    <ref bean="publisherService"/>
  </property>
  <property name="auditor">
    <ref bean="auditor"/>
  </property>
</bean>

<bean id="FXFWDMarketJPYCZK-3M-Market-Publisher" class="com.eurobase.ratemanager.external.out.RatePublisher">
  <constructor-arg index="0">
    <value>FXFWDMarketJPYCZK-3M-Market-Publisher</value>
  </constructor-arg>
  <property name="rateBean">
    <ref bean="FXFWDMarketJPYCZK-3M-Market-RateBean"/>
  </property>
  <property name="service">
    <ref bean="publisherService"/>
  </property>
  <property name="auditor">
    <ref bean="auditor"/>
  </property>
</bean>

<bean id="FXFWDMarketJPYCZK-4M-Market-Publisher" class="com.eurobase.ratemanager.external.out.RatePublisher">
  <constructor-arg index="0">
    <value>FXFWDMarketJPYCZK-4M-Market-Publisher</value>
  </constructor-arg>
  <property name="rateBean">
    <ref bean="FXFWDMarketJPYCZK-4M-Market-RateBean"/>
  </property>
  <property name="service">
    <ref bean="publisherService"/>
  </property>
  <property name="auditor">
    <ref bean="auditor"/>
  </property>
</bean>

<bean id="FXFWDMarketJPYCZK-5M-Market-Publisher" class="com.eurobase.ratemanager.external.out.RatePublisher">
  <constructor-arg index="0">
    <value>FXFWDMarketJPYCZK-5M-Market-Publisher</value>
  </constructor-arg>
  <property name="rateBean">
    <ref bean="FXFWDMarketJPYCZK-5M-Market-RateBean"/>
  </property>
  <property name="service">
    <ref bean="publisherService"/>
  </property>
  <property name="auditor">
    <ref bean="auditor"/>
  </property>
</bean>

<bean id="FXFWDMarketJPYCZK-6M-Market-Publisher" class="com.eurobase.ratemanager.external.out.RatePublisher">
  <constructor-arg index="0">
    <value>FXFWDMarketJPYCZK-6M-Market-Publisher</value>
  </constructor-arg>
  <property name="rateBean">
    <ref bean="FXFWDMarketJPYCZK-6M-Market-RateBean"/>
  </property>
  <property name="service">
    <ref bean="publisherService"/>
  </property>
  <property name="auditor">
    <ref bean="auditor"/>
  </property>
</bean>

<bean id="FXFWDMarketJPYCZK-7M-Market-Publisher" class="com.eurobase.ratemanager.external.out.RatePublisher">
  <constructor-arg index="0">
    <value>FXFWDMarketJPYCZK-7M-Market-Publisher</value>
  </constructor-arg>
  <property name="rateBean">
    <ref bean="FXFWDMarketJPYCZK-7M-Market-RateBean"/>
  </property>
  <property name="service">
    <ref bean="publisherService"/>
  </property>
  <property name="auditor">
    <ref bean="auditor"/>
  </property>
</bean>

<bean id="FXFWDMarketJPYCZK-8M-Market-Publisher" class="com.eurobase.ratemanager.external.out.RatePublisher">
  <constructor-arg index="0">
    <value>FXFWDMarketJPYCZK-8M-Market-Publisher</value>
  </constructor-arg>
  <property name="rateBean">
    <ref bean="FXFWDMarketJPYCZK-8M-Market-RateBean"/>
  </property>
  <property name="service">
    <ref bean="publisherService"/>
  </property>
  <property name="auditor">
    <ref bean="auditor"/>
  </property>
</bean>

<bean id="FXFWDMarketJPYCZK-9M-Market-Publisher" class="com.eurobase.ratemanager.external.out.RatePublisher">
  <constructor-arg index="0">
    <value>FXFWDMarketJPYCZK-9M-Market-Publisher</value>
  </constructor-arg>
  <property name="rateBean">
    <ref bean="FXFWDMarketJPYCZK-9M-Market-RateBean"/>
  </property>
  <property name="service">
    <ref bean="publisherService"/>
  </property>
  <property name="auditor">
    <ref bean="auditor"/>
  </property>
</bean>

<bean id="FXFWDMarketJPYCZK-10M-Market-Publisher" class="com.eurobase.ratemanager.external.out.RatePublisher">
  <constructor-arg index="0">
    <value>FXFWDMarketJPYCZK-10M-Market-Publisher</value>
  </constructor-arg>
  <property name="rateBean">
    <ref bean="FXFWDMarketJPYCZK-10M-Market-RateBean"/>
  </property>
  <property name="service">
    <ref bean="publisherService"/>
  </property>
  <property name="auditor">
    <ref bean="auditor"/>
  </property>
</bean>

<bean id="FXFWDMarketJPYCZK-11M-Market-Publisher" class="com.eurobase.ratemanager.external.out.RatePublisher">
  <constructor-arg index="0">
    <value>FXFWDMarketJPYCZK-11M-Market-Publisher</value>
  </constructor-arg>
  <property name="rateBean">
    <ref bean="FXFWDMarketJPYCZK-11M-Market-RateBean"/>
  </property>
  <property name="service">
    <ref bean="publisherService"/>
  </property>
  <property name="auditor">
    <ref bean="auditor"/>
  </property>
</bean>

<bean id="FXFWDMarketJPYCZK-1Y-Market-Publisher" class="com.eurobase.ratemanager.external.out.RatePublisher">
  <constructor-arg index="0">
    <value>FXFWDMarketJPYCZK-1Y-Market-Publisher</value>
  </constructor-arg>
  <property name="rateBean">
    <ref bean="FXFWDMarketJPYCZK-1Y-Market-RateBean"/>
  </property>
  <property name="service">
    <ref bean="publisherService"/>
  </property>
  <property name="auditor">
    <ref bean="auditor"/>
  </property>
</bean>


</beans>