<?xml version="1.0" encoding="UTF-8"?>
<?xml-stylesheet href="persister-table.xsl" type="text/xsl"?>
<beans xmlns="http://www.springframework.org/schema/beans"
       xmlns:xsi="http://www.w3.org/2001/XMLSchema-instance"
       xmlns:aop="http://www.springframework.org/schema/aop"
       xmlns:context="http://www.springframework.org/schema/context"
       xsi:schemaLocation="http://www.springframework.org/schema/beans 
                           http://www.springframework.org/schema/beans/spring-beans-2.5.xsd
                           http://www.springframework.org/schema/aop 
                           http://www.springframework.org/schema/aop/spring-aop-2.5.xsd
                           http://www.springframework.org/schema/context 
                           http://www.springframework.org/schema/context/spring-context-2.5.xsd">

<bean id="FXFWDMarketTRYSEK-ON-Market-XRateCalculator" class="com.eurobase.ratemanager.processing.generator.CrossRateGeneratorImpl2" init-method="init">
  <property name="currencyPair">
    <value>TRYSEK</value>
  </property>
  <property name="category">
    <value>Market</value>
  </property>
  <property name="tenor">
    <value>ON</value>
  </property>
  <property name="majorCurrencyPair">
    <value>USDTRY</value>
  </property>
  <property name="minorCurrencyPair">
    <value>USDSEK</value>
  </property>
  <property name="writer">
    <ref bean="XRateStore-FXFWDMarketTRYSEK-ON-Market"/>
  </property>
  <property name="factory">
    <ref bean="DefaultRateDatumFactory"/>
  </property>
  <property name="crossRateCalculator">
    <ref bean="crossRateCalculator-FXFWDMarketTRYSEK-ON-Market"/>
  </property>
  <property name="multicastEventSystem">
    <ref bean="multicastEventSystem" /> 
  </property>
  <property name="stores">
    <value>Controller,Controller,Controller,Controller</value> 
  </property>
  <property name="crossRateRetriever">
    <ref bean="crossrateengine" /> 
  </property>
</bean>

<bean id="crossRateCalculator-FXFWDMarketTRYSEK-ON-Market" class="com.eurobase.ratemanager.crossrate.CrossRateCalculatorImpl">
  <constructor-arg index="0">
    <ref bean="dbConnector"/>
  </constructor-arg>
</bean>

<bean id="FXFWDMarketTRYSEK-TN-Market-XRateCalculator" class="com.eurobase.ratemanager.processing.generator.CrossRateGeneratorImpl2" init-method="init">
  <property name="currencyPair">
    <value>TRYSEK</value>
  </property>
  <property name="category">
    <value>Market</value>
  </property>
  <property name="tenor">
    <value>TN</value>
  </property>
  <property name="majorCurrencyPair">
    <value>USDTRY</value>
  </property>
  <property name="minorCurrencyPair">
    <value>USDSEK</value>
  </property>
  <property name="writer">
    <ref bean="XRateStore-FXFWDMarketTRYSEK-TN-Market"/>
  </property>
  <property name="factory">
    <ref bean="DefaultRateDatumFactory"/>
  </property>
  <property name="crossRateCalculator">
    <ref bean="crossRateCalculator-FXFWDMarketTRYSEK-TN-Market"/>
  </property>
  <property name="multicastEventSystem">
    <ref bean="multicastEventSystem" /> 
  </property>
  <property name="stores">
    <value>Controller,Controller,Controller,Controller</value> 
  </property>
  <property name="crossRateRetriever">
    <ref bean="crossrateengine" /> 
  </property>
</bean>

<bean id="crossRateCalculator-FXFWDMarketTRYSEK-TN-Market" class="com.eurobase.ratemanager.crossrate.CrossRateCalculatorImpl">
  <constructor-arg index="0">
    <ref bean="dbConnector"/>
  </constructor-arg>
</bean>

<bean id="FXFWDMarketTRYSEK-SN-Market-XRateCalculator" class="com.eurobase.ratemanager.processing.generator.CrossRateGeneratorImpl2" init-method="init">
  <property name="currencyPair">
    <value>TRYSEK</value>
  </property>
  <property name="category">
    <value>Market</value>
  </property>
  <property name="tenor">
    <value>SN</value>
  </property>
  <property name="majorCurrencyPair">
    <value>USDTRY</value>
  </property>
  <property name="minorCurrencyPair">
    <value>USDSEK</value>
  </property>
  <property name="writer">
    <ref bean="XRateStore-FXFWDMarketTRYSEK-SN-Market"/>
  </property>
  <property name="factory">
    <ref bean="DefaultRateDatumFactory"/>
  </property>
  <property name="crossRateCalculator">
    <ref bean="crossRateCalculator-FXFWDMarketTRYSEK-SN-Market"/>
  </property>
  <property name="multicastEventSystem">
    <ref bean="multicastEventSystem" /> 
  </property>
  <property name="stores">
    <value>Controller,Controller,Controller,Controller</value> 
  </property>
  <property name="crossRateRetriever">
    <ref bean="crossrateengine" /> 
  </property>
</bean>

<bean id="crossRateCalculator-FXFWDMarketTRYSEK-SN-Market" class="com.eurobase.ratemanager.crossrate.CrossRateCalculatorImpl">
  <constructor-arg index="0">
    <ref bean="dbConnector"/>
  </constructor-arg>
</bean>

<bean id="FXFWDMarketTRYSEK-1W-Market-XRateCalculator" class="com.eurobase.ratemanager.processing.generator.CrossRateGeneratorImpl2" init-method="init">
  <property name="currencyPair">
    <value>TRYSEK</value>
  </property>
  <property name="category">
    <value>Market</value>
  </property>
  <property name="tenor">
    <value>1W</value>
  </property>
  <property name="majorCurrencyPair">
    <value>USDTRY</value>
  </property>
  <property name="minorCurrencyPair">
    <value>USDSEK</value>
  </property>
  <property name="writer">
    <ref bean="XRateStore-FXFWDMarketTRYSEK-1W-Market"/>
  </property>
  <property name="factory">
    <ref bean="DefaultRateDatumFactory"/>
  </property>
  <property name="crossRateCalculator">
    <ref bean="crossRateCalculator-FXFWDMarketTRYSEK-1W-Market"/>
  </property>
  <property name="multicastEventSystem">
    <ref bean="multicastEventSystem" /> 
  </property>
  <property name="stores">
    <value>Controller,Controller,Controller,Controller</value> 
  </property>
  <property name="crossRateRetriever">
    <ref bean="crossrateengine" /> 
  </property>
</bean>

<bean id="crossRateCalculator-FXFWDMarketTRYSEK-1W-Market" class="com.eurobase.ratemanager.crossrate.CrossRateCalculatorImpl">
  <constructor-arg index="0">
    <ref bean="dbConnector"/>
  </constructor-arg>
</bean>

<bean id="FXFWDMarketTRYSEK-2W-Market-XRateCalculator" class="com.eurobase.ratemanager.processing.generator.CrossRateGeneratorImpl2" init-method="init">
  <property name="currencyPair">
    <value>TRYSEK</value>
  </property>
  <property name="category">
    <value>Market</value>
  </property>
  <property name="tenor">
    <value>2W</value>
  </property>
  <property name="majorCurrencyPair">
    <value>USDTRY</value>
  </property>
  <property name="minorCurrencyPair">
    <value>USDSEK</value>
  </property>
  <property name="writer">
    <ref bean="XRateStore-FXFWDMarketTRYSEK-2W-Market"/>
  </property>
  <property name="factory">
    <ref bean="DefaultRateDatumFactory"/>
  </property>
  <property name="crossRateCalculator">
    <ref bean="crossRateCalculator-FXFWDMarketTRYSEK-2W-Market"/>
  </property>
  <property name="multicastEventSystem">
    <ref bean="multicastEventSystem" /> 
  </property>
  <property name="stores">
    <value>Controller,Controller,Controller,Controller</value> 
  </property>
  <property name="crossRateRetriever">
    <ref bean="crossrateengine" /> 
  </property>
</bean>

<bean id="crossRateCalculator-FXFWDMarketTRYSEK-2W-Market" class="com.eurobase.ratemanager.crossrate.CrossRateCalculatorImpl">
  <constructor-arg index="0">
    <ref bean="dbConnector"/>
  </constructor-arg>
</bean>

<bean id="FXFWDMarketTRYSEK-3W-Market-XRateCalculator" class="com.eurobase.ratemanager.processing.generator.CrossRateGeneratorImpl2" init-method="init">
  <property name="currencyPair">
    <value>TRYSEK</value>
  </property>
  <property name="category">
    <value>Market</value>
  </property>
  <property name="tenor">
    <value>3W</value>
  </property>
  <property name="majorCurrencyPair">
    <value>USDTRY</value>
  </property>
  <property name="minorCurrencyPair">
    <value>USDSEK</value>
  </property>
  <property name="writer">
    <ref bean="XRateStore-FXFWDMarketTRYSEK-3W-Market"/>
  </property>
  <property name="factory">
    <ref bean="DefaultRateDatumFactory"/>
  </property>
  <property name="crossRateCalculator">
    <ref bean="crossRateCalculator-FXFWDMarketTRYSEK-3W-Market"/>
  </property>
  <property name="multicastEventSystem">
    <ref bean="multicastEventSystem" /> 
  </property>
  <property name="stores">
    <value>Controller,Controller,Controller,Controller</value> 
  </property>
  <property name="crossRateRetriever">
    <ref bean="crossrateengine" /> 
  </property>
</bean>

<bean id="crossRateCalculator-FXFWDMarketTRYSEK-3W-Market" class="com.eurobase.ratemanager.crossrate.CrossRateCalculatorImpl">
  <constructor-arg index="0">
    <ref bean="dbConnector"/>
  </constructor-arg>
</bean>

<bean id="FXFWDMarketTRYSEK-1M-Market-XRateCalculator" class="com.eurobase.ratemanager.processing.generator.CrossRateGeneratorImpl2" init-method="init">
  <property name="currencyPair">
    <value>TRYSEK</value>
  </property>
  <property name="category">
    <value>Market</value>
  </property>
  <property name="tenor">
    <value>1M</value>
  </property>
  <property name="majorCurrencyPair">
    <value>USDTRY</value>
  </property>
  <property name="minorCurrencyPair">
    <value>USDSEK</value>
  </property>
  <property name="writer">
    <ref bean="XRateStore-FXFWDMarketTRYSEK-1M-Market"/>
  </property>
  <property name="factory">
    <ref bean="DefaultRateDatumFactory"/>
  </property>
  <property name="crossRateCalculator">
    <ref bean="crossRateCalculator-FXFWDMarketTRYSEK-1M-Market"/>
  </property>
  <property name="multicastEventSystem">
    <ref bean="multicastEventSystem" /> 
  </property>
  <property name="stores">
    <value>Controller,Controller,Controller,Controller</value> 
  </property>
  <property name="crossRateRetriever">
    <ref bean="crossrateengine" /> 
  </property>
</bean>

<bean id="crossRateCalculator-FXFWDMarketTRYSEK-1M-Market" class="com.eurobase.ratemanager.crossrate.CrossRateCalculatorImpl">
  <constructor-arg index="0">
    <ref bean="dbConnector"/>
  </constructor-arg>
</bean>

<bean id="FXFWDMarketTRYSEK-2M-Market-XRateCalculator" class="com.eurobase.ratemanager.processing.generator.CrossRateGeneratorImpl2" init-method="init">
  <property name="currencyPair">
    <value>TRYSEK</value>
  </property>
  <property name="category">
    <value>Market</value>
  </property>
  <property name="tenor">
    <value>2M</value>
  </property>
  <property name="majorCurrencyPair">
    <value>USDTRY</value>
  </property>
  <property name="minorCurrencyPair">
    <value>USDSEK</value>
  </property>
  <property name="writer">
    <ref bean="XRateStore-FXFWDMarketTRYSEK-2M-Market"/>
  </property>
  <property name="factory">
    <ref bean="DefaultRateDatumFactory"/>
  </property>
  <property name="crossRateCalculator">
    <ref bean="crossRateCalculator-FXFWDMarketTRYSEK-2M-Market"/>
  </property>
  <property name="multicastEventSystem">
    <ref bean="multicastEventSystem" /> 
  </property>
  <property name="stores">
    <value>Controller,Controller,Controller,Controller</value> 
  </property>
  <property name="crossRateRetriever">
    <ref bean="crossrateengine" /> 
  </property>
</bean>

<bean id="crossRateCalculator-FXFWDMarketTRYSEK-2M-Market" class="com.eurobase.ratemanager.crossrate.CrossRateCalculatorImpl">
  <constructor-arg index="0">
    <ref bean="dbConnector"/>
  </constructor-arg>
</bean>

<bean id="FXFWDMarketTRYSEK-3M-Market-XRateCalculator" class="com.eurobase.ratemanager.processing.generator.CrossRateGeneratorImpl2" init-method="init">
  <property name="currencyPair">
    <value>TRYSEK</value>
  </property>
  <property name="category">
    <value>Market</value>
  </property>
  <property name="tenor">
    <value>3M</value>
  </property>
  <property name="majorCurrencyPair">
    <value>USDTRY</value>
  </property>
  <property name="minorCurrencyPair">
    <value>USDSEK</value>
  </property>
  <property name="writer">
    <ref bean="XRateStore-FXFWDMarketTRYSEK-3M-Market"/>
  </property>
  <property name="factory">
    <ref bean="DefaultRateDatumFactory"/>
  </property>
  <property name="crossRateCalculator">
    <ref bean="crossRateCalculator-FXFWDMarketTRYSEK-3M-Market"/>
  </property>
  <property name="multicastEventSystem">
    <ref bean="multicastEventSystem" /> 
  </property>
  <property name="stores">
    <value>Controller,Controller,Controller,Controller</value> 
  </property>
  <property name="crossRateRetriever">
    <ref bean="crossrateengine" /> 
  </property>
</bean>

<bean id="crossRateCalculator-FXFWDMarketTRYSEK-3M-Market" class="com.eurobase.ratemanager.crossrate.CrossRateCalculatorImpl">
  <constructor-arg index="0">
    <ref bean="dbConnector"/>
  </constructor-arg>
</bean>

<bean id="FXFWDMarketTRYSEK-4M-Market-XRateCalculator" class="com.eurobase.ratemanager.processing.generator.CrossRateGeneratorImpl2" init-method="init">
  <property name="currencyPair">
    <value>TRYSEK</value>
  </property>
  <property name="category">
    <value>Market</value>
  </property>
  <property name="tenor">
    <value>4M</value>
  </property>
  <property name="majorCurrencyPair">
    <value>USDTRY</value>
  </property>
  <property name="minorCurrencyPair">
    <value>USDSEK</value>
  </property>
  <property name="writer">
    <ref bean="XRateStore-FXFWDMarketTRYSEK-4M-Market"/>
  </property>
  <property name="factory">
    <ref bean="DefaultRateDatumFactory"/>
  </property>
  <property name="crossRateCalculator">
    <ref bean="crossRateCalculator-FXFWDMarketTRYSEK-4M-Market"/>
  </property>
  <property name="multicastEventSystem">
    <ref bean="multicastEventSystem" /> 
  </property>
  <property name="stores">
    <value>Controller,Controller,Controller,Controller</value> 
  </property>
  <property name="crossRateRetriever">
    <ref bean="crossrateengine" /> 
  </property>
</bean>

<bean id="crossRateCalculator-FXFWDMarketTRYSEK-4M-Market" class="com.eurobase.ratemanager.crossrate.CrossRateCalculatorImpl">
  <constructor-arg index="0">
    <ref bean="dbConnector"/>
  </constructor-arg>
</bean>

<bean id="FXFWDMarketTRYSEK-5M-Market-XRateCalculator" class="com.eurobase.ratemanager.processing.generator.CrossRateGeneratorImpl2" init-method="init">
  <property name="currencyPair">
    <value>TRYSEK</value>
  </property>
  <property name="category">
    <value>Market</value>
  </property>
  <property name="tenor">
    <value>5M</value>
  </property>
  <property name="majorCurrencyPair">
    <value>USDTRY</value>
  </property>
  <property name="minorCurrencyPair">
    <value>USDSEK</value>
  </property>
  <property name="writer">
    <ref bean="XRateStore-FXFWDMarketTRYSEK-5M-Market"/>
  </property>
  <property name="factory">
    <ref bean="DefaultRateDatumFactory"/>
  </property>
  <property name="crossRateCalculator">
    <ref bean="crossRateCalculator-FXFWDMarketTRYSEK-5M-Market"/>
  </property>
  <property name="multicastEventSystem">
    <ref bean="multicastEventSystem" /> 
  </property>
  <property name="stores">
    <value>Controller,Controller,Controller,Controller</value> 
  </property>
  <property name="crossRateRetriever">
    <ref bean="crossrateengine" /> 
  </property>
</bean>

<bean id="crossRateCalculator-FXFWDMarketTRYSEK-5M-Market" class="com.eurobase.ratemanager.crossrate.CrossRateCalculatorImpl">
  <constructor-arg index="0">
    <ref bean="dbConnector"/>
  </constructor-arg>
</bean>

<bean id="FXFWDMarketTRYSEK-6M-Market-XRateCalculator" class="com.eurobase.ratemanager.processing.generator.CrossRateGeneratorImpl2" init-method="init">
  <property name="currencyPair">
    <value>TRYSEK</value>
  </property>
  <property name="category">
    <value>Market</value>
  </property>
  <property name="tenor">
    <value>6M</value>
  </property>
  <property name="majorCurrencyPair">
    <value>USDTRY</value>
  </property>
  <property name="minorCurrencyPair">
    <value>USDSEK</value>
  </property>
  <property name="writer">
    <ref bean="XRateStore-FXFWDMarketTRYSEK-6M-Market"/>
  </property>
  <property name="factory">
    <ref bean="DefaultRateDatumFactory"/>
  </property>
  <property name="crossRateCalculator">
    <ref bean="crossRateCalculator-FXFWDMarketTRYSEK-6M-Market"/>
  </property>
  <property name="multicastEventSystem">
    <ref bean="multicastEventSystem" /> 
  </property>
  <property name="stores">
    <value>Controller,Controller,Controller,Controller</value> 
  </property>
  <property name="crossRateRetriever">
    <ref bean="crossrateengine" /> 
  </property>
</bean>

<bean id="crossRateCalculator-FXFWDMarketTRYSEK-6M-Market" class="com.eurobase.ratemanager.crossrate.CrossRateCalculatorImpl">
  <constructor-arg index="0">
    <ref bean="dbConnector"/>
  </constructor-arg>
</bean>

<bean id="FXFWDMarketTRYSEK-7M-Market-XRateCalculator" class="com.eurobase.ratemanager.processing.generator.CrossRateGeneratorImpl2" init-method="init">
  <property name="currencyPair">
    <value>TRYSEK</value>
  </property>
  <property name="category">
    <value>Market</value>
  </property>
  <property name="tenor">
    <value>7M</value>
  </property>
  <property name="majorCurrencyPair">
    <value>USDTRY</value>
  </property>
  <property name="minorCurrencyPair">
    <value>USDSEK</value>
  </property>
  <property name="writer">
    <ref bean="XRateStore-FXFWDMarketTRYSEK-7M-Market"/>
  </property>
  <property name="factory">
    <ref bean="DefaultRateDatumFactory"/>
  </property>
  <property name="crossRateCalculator">
    <ref bean="crossRateCalculator-FXFWDMarketTRYSEK-7M-Market"/>
  </property>
  <property name="multicastEventSystem">
    <ref bean="multicastEventSystem" /> 
  </property>
  <property name="stores">
    <value>Controller,Controller,Controller,Controller</value> 
  </property>
  <property name="crossRateRetriever">
    <ref bean="crossrateengine" /> 
  </property>
</bean>

<bean id="crossRateCalculator-FXFWDMarketTRYSEK-7M-Market" class="com.eurobase.ratemanager.crossrate.CrossRateCalculatorImpl">
  <constructor-arg index="0">
    <ref bean="dbConnector"/>
  </constructor-arg>
</bean>

<bean id="FXFWDMarketTRYSEK-8M-Market-XRateCalculator" class="com.eurobase.ratemanager.processing.generator.CrossRateGeneratorImpl2" init-method="init">
  <property name="currencyPair">
    <value>TRYSEK</value>
  </property>
  <property name="category">
    <value>Market</value>
  </property>
  <property name="tenor">
    <value>8M</value>
  </property>
  <property name="majorCurrencyPair">
    <value>USDTRY</value>
  </property>
  <property name="minorCurrencyPair">
    <value>USDSEK</value>
  </property>
  <property name="writer">
    <ref bean="XRateStore-FXFWDMarketTRYSEK-8M-Market"/>
  </property>
  <property name="factory">
    <ref bean="DefaultRateDatumFactory"/>
  </property>
  <property name="crossRateCalculator">
    <ref bean="crossRateCalculator-FXFWDMarketTRYSEK-8M-Market"/>
  </property>
  <property name="multicastEventSystem">
    <ref bean="multicastEventSystem" /> 
  </property>
  <property name="stores">
    <value>Controller,Controller,Controller,Controller</value> 
  </property>
  <property name="crossRateRetriever">
    <ref bean="crossrateengine" /> 
  </property>
</bean>

<bean id="crossRateCalculator-FXFWDMarketTRYSEK-8M-Market" class="com.eurobase.ratemanager.crossrate.CrossRateCalculatorImpl">
  <constructor-arg index="0">
    <ref bean="dbConnector"/>
  </constructor-arg>
</bean>

<bean id="FXFWDMarketTRYSEK-9M-Market-XRateCalculator" class="com.eurobase.ratemanager.processing.generator.CrossRateGeneratorImpl2" init-method="init">
  <property name="currencyPair">
    <value>TRYSEK</value>
  </property>
  <property name="category">
    <value>Market</value>
  </property>
  <property name="tenor">
    <value>9M</value>
  </property>
  <property name="majorCurrencyPair">
    <value>USDTRY</value>
  </property>
  <property name="minorCurrencyPair">
    <value>USDSEK</value>
  </property>
  <property name="writer">
    <ref bean="XRateStore-FXFWDMarketTRYSEK-9M-Market"/>
  </property>
  <property name="factory">
    <ref bean="DefaultRateDatumFactory"/>
  </property>
  <property name="crossRateCalculator">
    <ref bean="crossRateCalculator-FXFWDMarketTRYSEK-9M-Market"/>
  </property>
  <property name="multicastEventSystem">
    <ref bean="multicastEventSystem" /> 
  </property>
  <property name="stores">
    <value>Controller,Controller,Controller,Controller</value> 
  </property>
  <property name="crossRateRetriever">
    <ref bean="crossrateengine" /> 
  </property>
</bean>

<bean id="crossRateCalculator-FXFWDMarketTRYSEK-9M-Market" class="com.eurobase.ratemanager.crossrate.CrossRateCalculatorImpl">
  <constructor-arg index="0">
    <ref bean="dbConnector"/>
  </constructor-arg>
</bean>

<bean id="FXFWDMarketTRYSEK-10M-Market-XRateCalculator" class="com.eurobase.ratemanager.processing.generator.CrossRateGeneratorImpl2" init-method="init">
  <property name="currencyPair">
    <value>TRYSEK</value>
  </property>
  <property name="category">
    <value>Market</value>
  </property>
  <property name="tenor">
    <value>10M</value>
  </property>
  <property name="majorCurrencyPair">
    <value>USDTRY</value>
  </property>
  <property name="minorCurrencyPair">
    <value>USDSEK</value>
  </property>
  <property name="writer">
    <ref bean="XRateStore-FXFWDMarketTRYSEK-10M-Market"/>
  </property>
  <property name="factory">
    <ref bean="DefaultRateDatumFactory"/>
  </property>
  <property name="crossRateCalculator">
    <ref bean="crossRateCalculator-FXFWDMarketTRYSEK-10M-Market"/>
  </property>
  <property name="multicastEventSystem">
    <ref bean="multicastEventSystem" /> 
  </property>
  <property name="stores">
    <value>Controller,Controller,Controller,Controller</value> 
  </property>
  <property name="crossRateRetriever">
    <ref bean="crossrateengine" /> 
  </property>
</bean>

<bean id="crossRateCalculator-FXFWDMarketTRYSEK-10M-Market" class="com.eurobase.ratemanager.crossrate.CrossRateCalculatorImpl">
  <constructor-arg index="0">
    <ref bean="dbConnector"/>
  </constructor-arg>
</bean>

<bean id="FXFWDMarketTRYSEK-11M-Market-XRateCalculator" class="com.eurobase.ratemanager.processing.generator.CrossRateGeneratorImpl2" init-method="init">
  <property name="currencyPair">
    <value>TRYSEK</value>
  </property>
  <property name="category">
    <value>Market</value>
  </property>
  <property name="tenor">
    <value>11M</value>
  </property>
  <property name="majorCurrencyPair">
    <value>USDTRY</value>
  </property>
  <property name="minorCurrencyPair">
    <value>USDSEK</value>
  </property>
  <property name="writer">
    <ref bean="XRateStore-FXFWDMarketTRYSEK-11M-Market"/>
  </property>
  <property name="factory">
    <ref bean="DefaultRateDatumFactory"/>
  </property>
  <property name="crossRateCalculator">
    <ref bean="crossRateCalculator-FXFWDMarketTRYSEK-11M-Market"/>
  </property>
  <property name="multicastEventSystem">
    <ref bean="multicastEventSystem" /> 
  </property>
  <property name="stores">
    <value>Controller,Controller,Controller,Controller</value> 
  </property>
  <property name="crossRateRetriever">
    <ref bean="crossrateengine" /> 
  </property>
</bean>

<bean id="crossRateCalculator-FXFWDMarketTRYSEK-11M-Market" class="com.eurobase.ratemanager.crossrate.CrossRateCalculatorImpl">
  <constructor-arg index="0">
    <ref bean="dbConnector"/>
  </constructor-arg>
</bean>

<bean id="FXFWDMarketTRYSEK-1Y-Market-XRateCalculator" class="com.eurobase.ratemanager.processing.generator.CrossRateGeneratorImpl2" init-method="init">
  <property name="currencyPair">
    <value>TRYSEK</value>
  </property>
  <property name="category">
    <value>Market</value>
  </property>
  <property name="tenor">
    <value>1Y</value>
  </property>
  <property name="majorCurrencyPair">
    <value>USDTRY</value>
  </property>
  <property name="minorCurrencyPair">
    <value>USDSEK</value>
  </property>
  <property name="writer">
    <ref bean="XRateStore-FXFWDMarketTRYSEK-1Y-Market"/>
  </property>
  <property name="factory">
    <ref bean="DefaultRateDatumFactory"/>
  </property>
  <property name="crossRateCalculator">
    <ref bean="crossRateCalculator-FXFWDMarketTRYSEK-1Y-Market"/>
  </property>
  <property name="multicastEventSystem">
    <ref bean="multicastEventSystem" /> 
  </property>
  <property name="stores">
    <value>Controller,Controller,Controller,Controller</value> 
  </property>
  <property name="crossRateRetriever">
    <ref bean="crossrateengine" /> 
  </property>
</bean>

<bean id="crossRateCalculator-FXFWDMarketTRYSEK-1Y-Market" class="com.eurobase.ratemanager.crossrate.CrossRateCalculatorImpl">
  <constructor-arg index="0">
    <ref bean="dbConnector"/>
  </constructor-arg>
</bean>


</beans>