<Collections xsi:noNamespaceSchemaLocation="file:///C:/Users/mtownsend/Desktop/arc/BOI%20-%20XML%20examples%20and%20NFRs/template.xsd" xmlns:xsi="http://www.w3.org/2001/XMLSchema-instance">
	<Collection>
		<DealType>Bond</DealType>
		<ExecType>0</ExecType>
		<TradeDate>20100329</TradeDate>
		<ExtRefNo>11945</ExtRefNo>
		<ExternalCustomer>BIGT</ExternalCustomer>
		<Direction>HOLDING</Direction>
		<Rate>0.045</Rate>
		<DealtCurrency>GBP</DealtCurrency>
		<DealtAmount>100</DealtAmount>
		<Book>Demo</Book>
		<ValueDate>20100330</ValueDate>
		<NI>UKT_4.50_07/03/19</NI>
	</Collection>
</Collections>
